openwebui_bootstrap/__init__.py
openwebui_bootstrap/cli.py
openwebui_bootstrap/config_manager.py
openwebui_bootstrap/exceptions.py
openwebui_bootstrap/logging_config.py
openwebui_bootstrap/models.py
openwebui_bootstrap/permission_service.py
openwebui_bootstrap/utils.py
openwebui_bootstrap/database/base.py
openwebui_bootstrap/database/sqlite.py
openwebui_bootstrap/resources/webui-0.7.2.db
openwebui_bootstrap-0.3.11.dist-info/METADATA
openwebui_bootstrap-0.3.11.dist-info/WHEEL
openwebui_bootstrap-0.3.11.dist-info/entry_points.txt
openwebui_bootstrap-0.3.11.dist-info/licenses/LICENSE
openwebui_bootstrap-0.3.11.dist-info/RECORD
