Metadata-Version: 2.4
Name: openwebui-bootstrap
Version: 0.3.11
Summary: Open WebUI Bootstrap - A tool to bootstrap Open WebUI deployments by writing configuration directly to the database
Project-URL: Homepage, https://gitlab.com/grenzfall/openwebui-bootstrap
Project-URL: Repository, https://gitlab.com/grenzfall/openwebui-bootstrap
Author-email: GreenQuark <greenquark@gmx.de>
License: MIT
License-File: LICENSE
Requires-Python: >=3.12
Requires-Dist: colorlog>=6.0.0
Requires-Dist: hatchling>=1.28.0
Requires-Dist: pydantic>=2.0.0
Requires-Dist: pyyaml>=6.0.0
